PandaPlyr/__init__.py
PandaPlyr/pandaplyr.py
PandaPlyr/utils.py
PandaPlyr/data/student_grades.csv
PandaPlyr/data/student_grades_by_year.csv
PandaPlyr/data/subject_categories.csv
PandaPlyr/data/titanic.csv
PandaPlyr-0.1.8.dist-info/LICENSE
PandaPlyr-0.1.8.dist-info/METADATA
PandaPlyr-0.1.8.dist-info/WHEEL
PandaPlyr-0.1.8.dist-info/top_level.txt
PandaPlyr-0.1.8.dist-info/RECORD
