Metadata-Version: 2.1
Name: PandaPlyr
Version: 0.1.8
Summary: The purpose of PandaPlyr is to make chained operations on pandas DataFrames easier and more readable.
Home-page: https://github.com/OlivierNDO/PandaPlyr/
Author: Nick Olivier
Author-email: Olivier_N@lynchburg.edu
Classifier: Programming Language :: Python :: 3
Classifier: License :: OSI Approved :: MIT License
Classifier: Operating System :: OS Independent
Requires-Python: >=3.6
License-File: LICENSE
Requires-Dist: numpy
Requires-Dist: pandas
